jprm/__init__.py
jprm/__main__.py
jprm-1.1.0.dist-info/LICENSE.txt
jprm-1.1.0.dist-info/METADATA
jprm-1.1.0.dist-info/WHEEL
jprm-1.1.0.dist-info/entry_points.txt
jprm-1.1.0.dist-info/top_level.txt
jprm-1.1.0.dist-info/zip-safe
jprm-1.1.0.dist-info/RECORD
