Metadata-Version: 2.1
Name: jprm
Version: 1.1.0
Summary: Jellyfin Plugin Repository Manager
Home-page: https://github.com/oddstr13/jellyfin-plugin-repository-manager
Author: Odd Stråbø
Author-email: oddstr13@openshell.no
Keywords: Jellyfin plugin repository compile publish development
Classifier: Programming Language :: Python :: 3 :: Only
Classifier: Programming Language :: Python :: 3.8
Classifier: Programming Language :: Python :: 3.9
Classifier: Programming Language :: Python :: 3.10
Classifier: Programming Language :: Python :: 3.11
Classifier: Programming Language :: Python :: 3.12
Classifier: License :: OSI Approved :: Mozilla Public License 2.0 (MPL 2.0)
Classifier: Operating System :: OS Independent
Classifier: Intended Audience :: Developers
Classifier: Intended Audience :: System Administrators
Classifier: Topic :: Software Development :: Build Tools
Classifier: Topic :: System :: Software Distribution
Requires-Python: >=3.8.1
License-File: LICENSE.txt
